steamid_converter/Converter.py
steamid_converter/__init__.py
steamid_converter-1.0.1.dist-info/LICENSE
steamid_converter-1.0.1.dist-info/METADATA
steamid_converter-1.0.1.dist-info/WHEEL
steamid_converter-1.0.1.dist-info/top_level.txt
steamid_converter-1.0.1.dist-info/RECORD
