Metadata-Version: 2.1
Name: steamid-converter
Version: 1.0.1
Summary: Package for easy conversion between steamID formats
Home-page: https://github.com/AlexHodgson/steamid-converter
Author: Alex Hodgson
Author-email: alex.hodgson@sci-fact.com
Classifier: Programming Language :: Python :: 3
Classifier: License :: OSI Approved :: MIT License
Classifier: Operating System :: OS Independent
Requires-Python: >=3.6
License-File: LICENSE
